[
     {
          "size": 3,
          "issue": []
     },
     {
          "size": 5,
          "issue": []
     },
     {
          "size": 10,
          "issue": [
               {
                    "id": 1,
                    "title": "顔",
                    "board": [
                         [1, 1, 0, 0, 0, 0, 0, 0, 1, 1],
                         [1, 0, 0, 0, 0, 0, 0, 0, 0, 1],
                         [1, 0, 1, 1, 1, 1, 0, 0, 0, 1],
                         [1, 1, 1, 1, 1, 1, 1, 0, 0, 1],
                         [1, 1, 0, 0, 1, 0, 0, 0, 0, 1],
                         [1, 1, 1, 0, 1, 0, 0, 0, 0, 1],
                         [1, 1, 1, 1, 1, 0, 0, 0, 1, 1],
                         [1, 1, 1, 1, 0, 0, 0, 0, 1, 1],
                         [1, 1, 1, 1, 1, 0, 0, 0, 1, 1],
                         [1, 1, 1, 0, 0, 0, 0, 1, 1, 1]
                    ]
               },
               {
                    "id": 2,
                    "title": "お化け",
                    "board": [
                         [0, 0, 0, 0, 0, 0, 0, 0, 0, 0],
                         [0, 0, 1, 0, 0, 0, 0, 0, 0, 0],
                         [0, 0, 0, 0, 0, 0, 0, 0, 0, 0],
                         [0, 0, 0, 0, 0, 0, 0, 1, 0, 0],
                         [0, 0, 0, 0, 0, 0, 0, 1, 0, 0],
                         [0, 0, 0, 0, 0, 0, 0, 1, 0, 0],
                         [0, 0, 0, 0, 0, 0, 0, 0, 0, 0],
                         [0, 0, 0, 0, 0, 0, 0, 0, 0, 0],
                         [0, 0, 0, 0, 0, 0, 1, 0, 1, 0],
                         [0, 0, 0, 0, 0, 0, 0, 0, 0, 0]
                    ]
               },
               {
                    "id": 3,
                    "title": "ねこ",
                    "board": [
                         [1, 1, 1, 1, 1, 1, 1, 1, 1, 1],
                         [1, 1, 1, 0, 1, 1, 1, 0, 1, 1],
                         [1, 1, 0, 0, 0, 1, 1, 0, 0, 1],
                         [1, 1, 0, 1, 0, 0, 0, 0, 0, 1],
                         [1, 0, 1, 1, 1, 1, 1, 1, 0, 0],
                         [1, 0, 0, 0, 1, 1, 0, 0, 1, 0],
                         [1, 0, 1, 1, 0, 1, 1, 1, 1, 0],
                         [1, 1, 0, 1, 1, 1, 1, 1, 0, 1],
                         [1, 1, 1, 0, 0, 0, 0, 0, 1, 1],
                         [1, 1, 1, 1, 1, 1, 1, 1, 1, 1]
                    ]
               },
               {
                    "id": 4,
                    "title": "りんご",
                    "board": [
                         [1, 1, 1, 1, 1, 1, 1, 1, 1, 1],
                         [1, 1, 1, 1, 0, 0, 0, 1, 1, 1],
                         [1, 1, 1, 1, 0, 1, 1, 1, 1, 1],
                         [1, 1, 0, 0, 0, 0, 0, 0, 1, 1],
                         [1, 0, 0, 0, 0, 0, 0, 0, 1, 1],
                         [1, 0, 0, 0, 0, 0, 0, 0, 0, 1],
                         [1, 0, 0, 0, 0, 0, 0, 0, 0, 1],
                         [1, 0, 0, 0, 0, 0, 0, 0, 0, 1],
                         [1, 0, 0, 0, 0, 0, 0, 0, 1, 1],
                         [1, 1, 0, 0, 0, 0, 0, 1, 1, 1]
                    ]
               },
               {
                    "id": 5,
                    "title": "鳥居",
                    "board": [
                         [1, 1, 1, 1, 1, 1, 1, 1, 1, 1],
                         [1, 1, 1, 1, 1, 1, 1, 1, 1, 1],
                         [0, 0, 0, 0, 0, 0, 0, 0, 0, 0],
                         [1, 1, 0, 1, 0, 0, 1, 0, 1, 1],
                         [1, 0, 0, 0, 0, 0, 0, 0, 0, 1],
                         [1, 1, 0, 1, 1, 1, 1, 0, 1, 1],
                         [1, 1, 0, 1, 1, 1, 1, 0, 1, 1],
                         [1, 1, 0, 1, 1, 1, 1, 0, 1, 1],
                         [1, 1, 0, 1, 1, 1, 1, 0, 1, 1],
                         [1, 1, 1, 1, 1, 1, 1, 1, 1, 1]
                    ]
               },
               {
                    "id": 6,
                    "title": "ゲームコントローラー",
                    "board": [
                         [1, 1, 1, 1, 0, 0, 1, 1, 1, 1],
                         [1, 1, 1, 1, 0, 0, 0, 1, 1, 1],
                         [1, 0, 0, 0, 0, 0, 0, 0, 0, 1],
                         [0, 0, 0, 0, 0, 0, 0, 0, 0, 0],
                         [0, 0, 0, 0, 0, 0, 0, 0, 0, 0],
                         [0, 0, 0, 0, 0, 0, 0, 0, 0, 0],
                         [0, 0, 0, 0, 0, 0, 0, 0, 0, 0],
                         [0, 0, 0, 0, 0, 0, 0, 0, 0, 0],
                         [1, 0, 0, 0, 1, 1, 0, 0, 0, 1],
                         [1, 1, 1, 1, 1, 1, 1, 1, 1, 1]
                    ]
               },
               {
                    "id": 7,
                    "title": "瓶",
                    "board": [
                         [1, 1, 1, 1, 1, 1, 1, 1, 1, 1],
                         [1, 1, 1, 1, 1, 1, 1, 1, 1, 1],
                         [1, 1, 1, 0, 0, 0, 1, 1, 1, 1],
                         [1, 1, 1, 1, 0, 1, 1, 1, 1, 1],
                         [1, 1, 1, 0, 0, 0, 1, 1, 1, 1],
                         [1, 1, 1, 0, 1, 0, 1, 1, 1, 1],
                         [1, 1, 1, 0, 1, 0, 1, 1, 1, 1],
                         [1, 1, 1, 0, 1, 0, 1, 1, 1, 1],
                         [1, 1, 1, 0, 0, 0, 1, 1, 1, 1],
                         [1, 1, 1, 1, 1, 1, 1, 1, 1, 1]
                    ]
               }
          ]
     }

]